{
  "QQQ_long": {
    "date": "2026-07-16",
    "last_status": "\u5c1a\u672a\u7a81\u7834"
  },
  "QQQ_short": {
    "date": "2026-07-16",
    "last_status": "\u5c1a\u672a\u7a81\u7834"
  },
  "AAPL_long": {
    "date": "2026-07-16",
    "last_status": "\u8a0a\u865f\u7121\u6548\uff08\u505c\u640d\u8ddd\u96e2\u904e\u5c0f\uff09"
  },
  "AAPL_short": {
    "date": "2026-07-16",
    "last_status": "\u5c1a\u672a\u7a81\u7834"
  },
  "MSFT_long": {
    "date": "2026-07-16",
    "last_status": "\u5df2\u51fa\u5834"
  },
  "MSFT_short": {
    "date": "2026-07-16",
    "last_status": "\u5c1a\u672a\u7a81\u7834"
  },
  "NVDA_long": {
    "date": "2026-07-16",
    "last_status": "\u5c1a\u672a\u7a81\u7834"
  },
  "NVDA_short": {
    "date": "2026-07-16",
    "last_status": "\u8a0a\u865f\u7121\u6548\uff08\u505c\u640d\u8ddd\u96e2\u904e\u5c0f\uff09"
  },
  "TSLA_long": {
    "date": "2026-07-16",
    "last_status": "\u5df2\u51fa\u5834"
  },
  "TSLA_short": {
    "date": "2026-07-16",
    "last_status": "\u5c1a\u672a\u7a81\u7834"
  },
  "AMZN_long": {
    "date": "2026-07-16",
    "last_status": "\u5c1a\u672a\u7a81\u7834"
  },
  "AMZN_short": {
    "date": "2026-07-16",
    "last_status": "\u5c1a\u672a\u7a81\u7834"
  },
  "GOOGL_long": {
    "date": "2026-07-16",
    "last_status": "\u5c1a\u672a\u7a81\u7834"
  },
  "GOOGL_short": {
    "date": "2026-07-16",
    "last_status": "\u5c1a\u672a\u7a81\u7834"
  },
  "META_long": {
    "date": "2026-07-16",
    "last_status": "\u5c1a\u672a\u7a81\u7834"
  },
  "META_short": {
    "date": "2026-07-16",
    "last_status": "\u5c1a\u672a\u7a81\u7834"
  },
  "INTC_long": {
    "date": "2026-07-16",
    "last_status": "\u5c1a\u672a\u7a81\u7834"
  },
  "INTC_short": {
    "date": "2026-07-16",
    "last_status": "\u6301\u5009\u4e2d"
  },
  "XOM_long": {
    "date": "2026-07-16",
    "last_status": "\u5df2\u51fa\u5834"
  },
  "XOM_short": {
    "date": "2026-07-16",
    "last_status": "\u5c1a\u672a\u7a81\u7834"
  },
  "JNJ_long": {
    "date": "2026-07-16",
    "last_status": "\u5c1a\u672a\u7a81\u7834"
  },
  "JNJ_short": {
    "date": "2026-07-16",
    "last_status": "\u5c1a\u672a\u7a81\u7834"
  },
  "KO_long": {
    "date": "2026-07-16",
    "last_status": "\u5c1a\u672a\u7a81\u7834"
  },
  "KO_short": {
    "date": "2026-07-16",
    "last_status": "\u5c1a\u672a\u7a81\u7834"
  },
  "PYPL_long": {
    "date": "2026-07-16",
    "last_status": "\u6301\u5009\u4e2d"
  },
  "PYPL_short": {
    "date": "2026-07-16",
    "last_status": "\u5c1a\u672a\u7a81\u7834"
  },
  "DIS_long": {
    "date": "2026-07-16",
    "last_status": "\u7b49\u5f85\u56de\u6e2c\u78ba\u8a8d"
  },
  "DIS_short": {
    "date": "2026-07-16",
    "last_status": "\u5c1a\u672a\u7a81\u7834"
  },
  "BA_long": {
    "date": "2026-07-16",
    "last_status": "\u5c1a\u672a\u7a81\u7834"
  },
  "BA_short": {
    "date": "2026-07-16",
    "last_status": "\u5c1a\u672a\u7a81\u7834"
  }
}